README.md
setup.py
logging_helpers/__init__.py
logging_helpers/compat.py
logging_helpers/django_middleware.py
logging_helpers/flask_request_log.py
logging_helpers.egg-info/PKG-INFO
logging_helpers.egg-info/SOURCES.txt
logging_helpers.egg-info/dependency_links.txt
logging_helpers.egg-info/top_level.txt