Metadata-Version: 1.0
Name: logging-helpers
Version: 0.10.1
Summary: Some logging helpers: Context, key-value rendering, etc.
Home-page: UNKNOWN
Author: Stas Kaledin
Author-email: staskaledin@gmail.com
License: UNKNOWN
Platform: UNKNOWN
